guolei_py3_zkhb/__init__.py
guolei_py3_zkhb/pmf.py
guolei_py3_zkhb/library/__init__.py
guolei_py3_zkhb/library/pfm.py
guolei_py3_zkhb-2.1.2.dist-info/LICENSE
guolei_py3_zkhb-2.1.2.dist-info/METADATA
guolei_py3_zkhb-2.1.2.dist-info/WHEEL
guolei_py3_zkhb-2.1.2.dist-info/top_level.txt
guolei_py3_zkhb-2.1.2.dist-info/RECORD
